COPYING.txt
LICENSE.txt
MANIFEST.in
README.txt
setup.py
canary/__init__.py
docs/index.html
docs/images/pCanary.jpg
docs/images/pCanaryLogo.jpg
pCanary/Cage.py
pCanary/Knowledge.py
pCanary/__init__.py
pCanary/__main__.py
pCanary.egg-info/PKG-INFO
pCanary.egg-info/SOURCES.txt
pCanary.egg-info/dependency_links.txt
pCanary.egg-info/top_level.txt