Metadata-Version: 1.0
Name: pCanary
Version: 0.0.5
Summary: pCanary is a opensource recipe and ore lookupapplication for Minecraft
Home-page: http://tinyurl.com/pCanary81
Author: Jeremiah O'Neal
Author-email: we6jbo@gmail.com
License: GNU GPL3
Keywords: minecraft recipe ore graphical
Platform: UNKNOWN
Classifier: Programming Language :: Python
Classifier: Programming Language :: Python :: 3
Classifier: Environment :: X11 Applications
Classifier: Intended Audience :: End Users/Desktop
Classifier: Natural Language :: English
Classifier: Operating System :: POSIX :: Linux
Classifier: Development Status :: 3 - Alpha
Classifier: License :: OSI Approved :: GNU General Public License v3 (GPLv3)
